Common/CommonUtls.py
Common/__init__.py
DuyanCommon/CommonUtls.py
DuyanCommon/Error.py
DuyanCommon/LogUtils.py
DuyanCommon/MongoDBUtils.py
DuyanCommon/MysqlDBUtils.py
DuyanCommon/RedisUtils.py
DuyanCommon/SQLAlchemyUtils.py
DuyanCommon/SeleniumUtils.py
DuyanCommon/__init__.py
Logger/LogUtils.py
Logger/__init__.py
MongoDB/MongoDBUtils.py
MongoDB/__init__.py
MySqlDB/MysqlDBUtils.py
MySqlDB/SQLAlchemyUtils.py
MySqlDB/__init__.py
Redis/RedisUtils.py
Redis/__init__.py
DuyanUtils-1.0.4.dist-info/LICENSE
DuyanUtils-1.0.4.dist-info/METADATA
DuyanUtils-1.0.4.dist-info/WHEEL
DuyanUtils-1.0.4.dist-info/top_level.txt
DuyanUtils-1.0.4.dist-info/RECORD
