Metadata-Version: 2.1
Name: DuyanUtils
Version: 1.0.4
Summary: 常用工具 轻量化处理
Home-page: UNKNOWN
Author: Jianguo.Wang
Author-email: chunyang.wang@duyansoft.com
License: UNKNOWN
Platform: UNKNOWN
Classifier: Programming Language :: Python :: 3
Classifier: License :: OSI Approved :: MIT License
Classifier: Operating System :: OS Independent
Requires-Python: >=3.6
License-File: LICENSE
